sartopo_python/__init__.py
sartopo_python/sartopo_python.py
sartopo_python/test.py
sartopo_python-2.0.0.dist-info/LICENSE
sartopo_python-2.0.0.dist-info/METADATA
sartopo_python-2.0.0.dist-info/WHEEL
sartopo_python-2.0.0.dist-info/top_level.txt
sartopo_python-2.0.0.dist-info/RECORD
