Metadata-Version: 2.1
Name: sartopo_python
Version: 2.0.0
Summary: Python interface to unofficial CalTopo/SARTopo API
Home-page: https://github.com/ncssar/sartopo_python
Download-URL: https://github.com/ncssar/sartopo_python/archive/2.0.0.tar.gz
Author: Tom Grundy
Author-email: nccaves@yahoo.com
Classifier: Programming Language :: Python :: 3
Classifier: License :: OSI Approved :: GNU General Public License v3 (GPLv3)
Classifier: Operating System :: OS Independent
Classifier: Development Status :: 4 - Beta
License-File: LICENSE
Requires-Dist: Shapely >=2.0.2
Requires-Dist: requests
